chainollama/__init__.py
chainollama/resources/chain_system_prompt.md
chainollama-0.7.dist-info/LICENSE
chainollama-0.7.dist-info/METADATA
chainollama-0.7.dist-info/WHEEL
chainollama-0.7.dist-info/top_level.txt
chainollama-0.7.dist-info/RECORD
